cmaketools/__init__.py
cmaketools/internal/__init__.py
cmaketools/internal/updatesources/FileGenerator.py
cmaketools/internal/updatesources/FileSearch.py
cmaketools/internal/updatesources/HelpFormatter.py
cmaketools/internal/updatesources/LineProcessor.py
cmaketools/internal/updatesources/PathResolver.py
cmaketools/internal/updatesources/Project.py
cmaketools/internal/updatesources/ResolveDirectoryAction.py
cmaketools/internal/updatesources/__init__.py
cmaketools/updatesources.py
updatesources-0.1.0.dist-info/entry_points.txt
updatesources-0.1.0.dist-info/WHEEL
updatesources-0.1.0.dist-info/METADATA
updatesources-0.1.0.dist-info/RECORD
